llmdantic/__init__.py
llmdantic/llmdantic.py
llmdantic/core/__init__.py
llmdantic/core/exceptions.py
llmdantic/core/utils.py
llmdantic/models/__init__.py
llmdantic/models/llm_config.py
llmdantic/models/llm_result.py
llmdantic/models/llm_usage.py
llmdantic/output_parsers/__init__.py
llmdantic/output_parsers/output_parser.py
llmdantic/prompts/__init__.py
llmdantic/prompts/format_instructions.py
llmdantic/prompts/prompt_builder.py
llmdantic-1.0.3.dist-info/LICENSE
llmdantic-1.0.3.dist-info/WHEEL
llmdantic-1.0.3.dist-info/METADATA
llmdantic-1.0.3.dist-info/RECORD
