Metadata-Version: 2.1
Name: llmdantic
Version: 1.0.3
Summary: LLMdantic is a Python package that provides structured interaction with LLMs.
Author-email: firattamur <ftamur16@ku.edu.tr>
Requires-Python: >=3.8
Classifier: Intended Audience :: Developers
Classifier: License :: OSI Approved :: BSD License
Classifier: Programming Language :: Python :: 3
Classifier: Topic :: Software Development :: Libraries :: Python Modules
Requires-Dist: langchain >=0.1.6
Requires-Dist: langchain_openai >=0.0.5
Requires-Dist: regex >=2023.12.25
Requires-Dist: pytest ; extra == "test"
Requires-Dist: ruff ; extra == "test"
Requires-Dist: mypy ; extra == "test"
Requires-Dist: isort ; extra == "test"
Requires-Dist: black ; extra == "test"
Requires-Dist: black ; extra == "test"
Requires-Dist: flit ; extra == "test"
Requires-Dist: coverage ; extra == "test"
Requires-Dist: bump2version ; extra == "test"
Project-URL: Home, https://github.com/firattamur/llmdantic
Provides-Extra: test
